[
  {
    "key": "jvideo",
    "title": "Jesus Video",
    "image": "/images/jesus.png",
    "route": "/jvideo",
    "maxLessons": 61
  },
  {
    "key": "life",
    "title": "Life Issues",
    "image": "/images/life.png",
    "route": "/series/life",
    "maxLessons": 23
  },
  {
    "key": "ctc",
    "title": "Connect to Community",
    "image": "/images/community.png",
    "route": "/series/ctc",
    "maxLessons": 23
  },
  {
    "key": "obey",
    "title": "Obey",
    "image": "/images/obey.png",
    "route": "/series/obey",
    "maxLessons": 8
  },
  {
    "key": "give",
    "title": "Give",
    "image": "/images/give.png",
    "route": "/series/give",
    "maxLessons": 9
  },
  {
    "key": "relate",
    "title": "Relate",
    "image": "/images/relate.png",
    "route": "/series/relate",
    "maxLessons": 9
  },
  {
    "key": "serve",
    "title": "Serve",
    "image": "/images/serve.png",
    "route": "/series/serve",
    "maxLessons": 9
  },
  {
    "key": "hope",
    "title": "Seven Stories of Hope",
    "image": "/images/hope.png",
    "route": "/series/hope",
    "maxLessons": 7
  },
  {
    "key": "share",
    "title": "Share",
    "image": "/images/share.png",
    "route": "/series/share",
    "maxLessons": 9
  },
  {
    "key": "trust",
    "title": "Trust",
    "image": "/images/trust.png",
    "route": "/series/trust",
    "maxLessons": 17
  },
  {
    "key": "lead",
    "title": "Lead",
    "image": "/images/lead.png",
    "route": "/series/lead",
    "maxLessons": 25
  },
  {
    "key": "disciple",
    "title": "Disciple",
    "image": "/images/disciple.png",
    "route": "/series/disciple",
    "maxLessons": 8
  }
]
